core/__init__.py
core/dataProcessUtil.py
core/dubboUtil.py
core/httpUtil.py
core/jenkinsUtil.py
core/kafkaSender.py
core/kafkaUtil.py
core/mqttUtil.py
core/reidsUtil.py
core/run.py
core/testDataUtil.py
core/thirdPartInterface.py
core/utils.py
core/xmind2excel.py
core/bladeTest/__init__.py
core/bladeTest/app.py
core/bladeTest/app_layout.py
core/bladeTest/interactive.py
core/bladeTest/interactive_blade.py
core/bladeTest/interactive_jmeter.py
core/bladeTest/interactive_tcpcopy.py
core/bladeTest/interactive_testUtil.py
core/bladeTest/interactive_testUtils.py
core/bladeTest/interactive_tslbusiness.py
core/bladeTest/interactive_xmind.py
core/bladeTest/main.py
core/bladeTest/versionSuggestion.py
core/bladeTest/xmindStructure.jpg
core/bladeTest/bootstrap/.DS_Store
core/bladeTest/bootstrap/template.html
core/bladeTest/templates/.DS_Store
core/bladeTest/templates/kafkaWebClient.html
core/bladeTest/templates/play.html
core/bladeTest/templates/voice.mp3
core/jmeterTool/__init__.py
core/jmeterTool/har2jmeter.py
core/jmeterTool/swagger2jmeter.py
core/jmeterTool/har2jmeter_utils/__init__.py
core/jmeterTool/har2jmeter_utils/templates/jmeter.jinja
core/jmeterTool/jmeterzip/__init__.py
core/jmeterTool/jmeterzip/readMe.txt
kframe/__init__.py
kframe/kframe.py
khandytool-0.2.72.dist-info/LICENSE
khandytool-0.2.72.dist-info/METADATA
khandytool-0.2.72.dist-info/WHEEL
khandytool-0.2.72.dist-info/entry_points.txt
khandytool-0.2.72.dist-info/top_level.txt
khandytool-0.2.72.dist-info/RECORD
