Metadata-Version: 2.1
Name: khandytool
Version: 0.2.72
Summary: khandytool, handy core in testing
Home-page: https://github.com/kevin72500/khandytool
Author: Ou Peng
Author-email: kevin72500@qq.com
License: UNKNOWN
Platform: UNKNOWN
Classifier: Programming Language :: Python :: 3
Classifier: License :: OSI Approved :: MIT License
Classifier: Operating System :: OS Independent
Requires-Dist: jsonpath (==0.82)
Requires-Dist: xmltodict (==0.13.0)
Requires-Dist: flashtext
Requires-Dist: fabric (==2.6.0)
Requires-Dist: pytest (==6.2.5)
Requires-Dist: pywebio (==1.6.0)
Requires-Dist: requests (==2.26.0)
Requires-Dist: loguru (==0.5.3)
Requires-Dist: jinja2 (==3.0.2)
Requires-Dist: openpyxl (==3.0.9)
Requires-Dist: xmindparser (==1.0.9)
Requires-Dist: jmespath (==0.10.0)
Requires-Dist: pymysql (==1.0.2)
Requires-Dist: swaggerjmx (==1.0.9)
Requires-Dist: faker (==8.12.1)
Requires-Dist: websockets (==10.1)
Requires-Dist: kafka-python (==2.0.2)
Requires-Dist: flask (==2.0.2)
Requires-Dist: Werkzeug (==2.0.2)
Requires-Dist: paho-mqtt (==1.5.1)
Requires-Dist: msgpack (==1.0.3)
Requires-Dist: redis (==4.1.3)
Requires-Dist: python-dotenv (==0.19.2)
Requires-Dist: jsonschema
Requires-Dist: tenacity
Requires-Dist: wget
Requires-Dist: pyttsx3
Requires-Dist: pyyaml
Requires-Dist: xlrd
Requires-Dist: pytest-html
Requires-Dist: pycrypto (==2.6.1) ; platform_system == "Darwin"
Requires-Dist: pycrypto (==2.6.1) ; platform_system == "Linux"
Requires-Dist: pycryptodome (==3.12.0) ; platform_system == "Windows"
